odoo/addons/sale_production_state/README.rst
odoo/addons/sale_production_state/__init__.py
odoo/addons/sale_production_state/__manifest__.py
odoo/addons/sale_production_state/i18n/sale_production_state.pot
odoo/addons/sale_production_state/models/__init__.py
odoo/addons/sale_production_state/models/sale_order.py
odoo/addons/sale_production_state/models/sale_order_line.py
odoo/addons/sale_production_state/readme/CONTRIBUTORS.rst
odoo/addons/sale_production_state/readme/DESCRIPTION.rst
odoo/addons/sale_production_state/static/description/icon.png
odoo/addons/sale_production_state/static/description/index.html
odoo/addons/sale_production_state/tests/__init__.py
odoo/addons/sale_production_state/tests/test_production_state.py
odoo/addons/sale_production_state/views/sale_order.xml
odoo14_addon_sale_production_state-14.0.1.0.1.dist-info/METADATA
odoo14_addon_sale_production_state-14.0.1.0.1.dist-info/WHEEL
odoo14_addon_sale_production_state-14.0.1.0.1.dist-info/top_level.txt
odoo14_addon_sale_production_state-14.0.1.0.1.dist-info/RECORD
