Metadata-Version: 2.1
Name: odoo14-addon-sale_production_state
Version: 14.0.1.0.1
Summary: Show the production state on the sale order
Home-page: https://github.com/OCA/sale-workflow
Author: Akretion, Odoo Community Association (OCA)
Author-email: support@odoo-community.org
License: AGPL-3
Classifier: Programming Language :: Python
Classifier: Framework :: Odoo
Classifier: Framework :: Odoo :: 14.0
Classifier: License :: OSI Approved :: GNU Affero General Public License v3
Requires-Python: >=3.6
Requires-Dist: odoo14-addon-mrp-sale-info
Requires-Dist: odoo<14.1dev,>=14.0a
